pyseter/__init__.py
pyseter/extract.py
pyseter/grade.py
pyseter/sort.py
pyseter-0.2.2.dist-info/licenses/LICENSE
pyseter-0.2.2.dist-info/METADATA
pyseter-0.2.2.dist-info/WHEEL
pyseter-0.2.2.dist-info/top_level.txt
pyseter-0.2.2.dist-info/RECORD
