Metadata-Version: 2.4
Name: pyseter
Version: 0.2.2
Summary: Sort images by an automatically generated ID before photo-ID
Author-email: "Philip T. Patton" <philtpatton@gmail.com>
License: MIT
Project-URL: Homepage, https://github.com/philpatton/pyseter
Project-URL: Changelog, https://github.com/username/your-package/blob/main/CHANGELOG.md
Project-URL: Documentation, https://philpatton.github.io/pyseter
Project-URL: Repository, https://github.com/philpatton/pyseter
Project-URL: Bug Tracker, https://github.com/philpatton/pyseter/issues
Keywords: individual identification,pytorch,marine mammal
Classifier: Development Status :: 3 - Alpha
Classifier: License :: OSI Approved :: MIT License
Classifier: Programming Language :: Python :: 3
Classifier: Programming Language :: Python :: 3.8
Classifier: Programming Language :: Python :: 3.9
Classifier: Programming Language :: Python :: 3.10
Classifier: Programming Language :: Python :: 3.11
Requires-Python: >=3.8
License-File: LICENSE
Requires-Dist: numpy>=1.21.0
Requires-Dist: pandas>=1.3.0
Requires-Dist: scikit-learn>=1.1.0
Requires-Dist: networkx>=2.6.0
Requires-Dist: matplotlib>=3.5.0
Requires-Dist: tqdm>=4.60.0
Requires-Dist: timm>=0.6.0
Requires-Dist: huggingface-hub>=0.16.0
Provides-Extra: dev
Requires-Dist: pytest>=7.0.0; extra == "dev"
Requires-Dist: pytest-cov>=4.0.0; extra == "dev"
Dynamic: license-file
